{"fr":60,"h":1030,"ip":0,"layers":[{"ind":3,"ty":4,"parent":2,"ks":{},"ip":0,"op":495.4,"st":0,"shapes":[{"ty":"rc","p":{"a":1,"k":[{"t":0,"s":[35,35],"i":{"x":[0,1],"y":[1,1]},"o":{"x":[0.5,0],"y":[0,0]}},{"t":48,"s":[225,35],"i":{"x":[1,1],"y":[1,1]},"o":{"x":[0,0],"y":[0,0]}},{"t":494.4,"s":[225,35],"h":1}]},"r":{"a":0,"k":0},"s":{"a":1,"k":[{"t":0,"s":[70,70],"i":{"x":[0,1],"y":[1,1]},"o":{"x":[0.5,0],"y":[0,0]}},{"t":48,"s":[450,70],"i":{"x":[1,1],"y":[1,1]},"o":{"x":[0,0],"y":[0,0]}},{"t":494.4,"s":[450,70],"h":1}]}},{"ty":"fl","c":{"a":0,"k":[0,0,0]},"o":{"a":0,"k":100}}]},{"ind":2,"ty":3,"parent":1,"ks":{"a":{"a":1,"k":[{"t":0,"s":[35,35],"i":{"x":[0,1],"y":[1,1]},"o":{"x":[0.5,0],"y":[0,0]}},{"t":48,"s":[225,35],"i":{"x":[1,1],"y":[1,1]},"o":{"x":[0,0],"y":[0,0]}},{"t":494.4,"s":[225,35],"h":1}]},"p":{"a":1,"k":[{"t":0,"s":[755,275],"i":{"x":[1,0],"y":[1,1]},"o":{"x":[0,0.501],"y":[0,0]}},{"t":48,"s":[755,465],"i":{"x":[1,1],"y":[1,1]},"o":{"x":[0,0],"y":[0,0]}},{"t":60,"s":[755,465],"i":{"x":[1,0],"y":[1,1]},"o":{"x":[0,0.5],"y":[0,0]}},{"t":108,"s":[755,565],"i":{"x":[1,1],"y":[1,1]},"o":{"x":[0,0],"y":[0,0]}},{"t":494.4,"s":[755,565],"h":1}]},"r":{"a":0,"k":90}},"ip":0,"op":495.4,"st":0},{"ind":5,"ty":4,"parent":4,"ks":{},"ip":0,"op":495.4,"st":0,"shapes":[{"ty":"rc","p":{"a":1,"k":[{"t":0,"s":[225,35],"i":{"x":[0,1],"y":[1,1]},"o":{"x":[0.5,0],"y":[0,0]}},{"t":48,"s":[35,35],"i":{"x":[1,1],"y":[1,1]},"o":{"x":[0,0],"y":[0,0]}},{"t":60,"s":[35,35],"i":{"x":[1,0],"y":[1,1]},"o":{"x":[0,0.5],"y":[0,0]}},{"t":108,"s":[35,225],"i":{"x":[1,1],"y":[1,1]},"o":{"x":[0,0],"y":[0,0]}},{"t":494.4,"s":[35,225],"h":1}]},"r":{"a":0,"k":0},"s":{"a":1,"k":[{"t":0,"s":[450,70],"i":{"x":[0,1],"y":[1,1]},"o":{"x":[0.5,0],"y":[0,0]}},{"t":48,"s":[70,70],"i":{"x":[1,1],"y":[1,1]},"o":{"x":[0,0],"y":[0,0]}},{"t":60,"s":[70,70],"i":{"x":[1,0],"y":[1,1]},"o":{"x":[0,0.5],"y":[0,0]}},{"t":108,"s":[70,450],"i":{"x":[1,1],"y":[1,1]},"o":{"x":[0,0],"y":[0,0]}},{"t":494.4,"s":[70,450],"h":1}]}},{"ty":"fl","c":{"a":0,"k":[0,0,0]},"o":{"a":0,"k":100}}]},{"ind":4,"ty":3,"parent":1,"ks":{"a":{"a":1,"k":[{"t":0,"s":[225,35],"i":{"x":[0,1],"y":[1,1]},"o":{"x":[0.5,0],"y":[0,0]}},{"t":48,"s":[35,35],"i":{"x":[1,1],"y":[1,1]},"o":{"x":[0,0],"y":[0,0]}},{"t":60,"s":[35,35],"i":{"x":[1,0],"y":[1,1]},"o":{"x":[0,0.5],"y":[0,0]}},{"t":108,"s":[35,225],"i":{"x":[1,1],"y":[1,1]},"o":{"x":[0,0],"y":[0,0]}},{"t":494.4,"s":[35,225],"h":1}]},"p":{"a":1,"k":[{"t":0,"s":[755,565],"i":{"x":[1,0.001],"y":[1,1]},"o":{"x":[0,0.502],"y":[0,0]}},{"t":48,"s":[755,755],"i":{"x":[1,1],"y":[1,1]},"o":{"x":[0,0],"y":[0,0]}},{"t":60,"s":[755,755],"i":{"x":[0,1],"y":[1,1]},"o":{"x":[0.502,0],"y":[0,0]}},{"t":108,"s":[565,755],"i":{"x":[1,1],"y":[1,1]},"o":{"x":[0,0],"y":[0,0]}},{"t":494.4,"s":[565,755],"h":1}]},"r":{"a":0,"k":90}},"ip":0,"op":495.4,"st":0},{"ind":7,"ty":4,"parent":6,"ks":{},"ip":0,"op":495.4,"st":0,"shapes":[{"ty":"rc","p":{"a":1,"k":[{"t":0,"s":[225,35],"i":{"x":[1,1],"y":[1,1]},"o":{"x":[0,0],"y":[0,0]}},{"t":60,"s":[225,35],"i":{"x":[0,1],"y":[1,1]},"o":{"x":[0.5,0],"y":[0,0]}},{"t":108,"s":[35,35],"i":{"x":[1,1],"y":[1,1]},"o":{"x":[0,0],"y":[0,0]}},{"t":494.4,"s":[35,35],"h":1}]},"r":{"a":0,"k":0},"s":{"a":1,"k":[{"t":0,"s":[450,70],"i":{"x":[1,1],"y":[1,1]},"o":{"x":[0,0],"y":[0,0]}},{"t":60,"s":[450,70],"i":{"x":[0,1],"y":[1,1]},"o":{"x":[0.5,0],"y":[0,0]}},{"t":108,"s":[70,70],"i":{"x":[1,1],"y":[1,1]},"o":{"x":[0,0],"y":[0,0]}},{"t":494.4,"s":[70,70],"h":1}]}},{"ty":"fl","c":{"a":0,"k":[0,0,0]},"o":{"a":0,"k":100}}]},{"ind":6,"ty":3,"parent":1,"ks":{"p":{"a":1,"k":[{"t":0,"s":[340,720],"i":{"x":[0,1],"y":[1,1]},"o":{"x":[0.5,0],"y":[0,0]}},{"t":48,"s":[240,720],"i":{"x":[1,1],"y":[1,1]},"o":{"x":[0,0],"y":[0,0]}},{"t":494.4,"s":[240,720],"h":1}]}},"ip":0,"op":495.4,"st":0},{"ind":9,"ty":4,"parent":8,"ks":{},"ip":0,"op":495.4,"st":0,"shapes":[{"ty":"rc","p":{"a":1,"k":[{"t":0,"s":[35,35],"i":{"x":[0,1],"y":[1,1]},"o":{"x":[0.5,0],"y":[0,0]}},{"t":48,"s":[225,35],"i":{"x":[1,1],"y":[1,1]},"o":{"x":[0,0],"y":[0,0]}},{"t":494.4,"s":[225,35],"h":1}]},"r":{"a":0,"k":0},"s":{"a":1,"k":[{"t":0,"s":[70,70],"i":{"x":[0,1],"y":[1,1]},"o":{"x":[0.5,0],"y":[0,0]}},{"t":48,"s":[450,70],"i":{"x":[1,1],"y":[1,1]},"o":{"x":[0,0],"y":[0,0]}},{"t":494.4,"s":[450,70],"h":1}]}},{"ty":"fl","c":{"a":0,"k":[0,0,0]},"o":{"a":0,"k":100}}]},{"ind":8,"ty":3,"parent":1,"ks":{"a":{"a":1,"k":[{"t":0,"s":[35,35],"i":{"x":[0,1],"y":[1,1]},"o":{"x":[0.5,0],"y":[0,0]}},{"t":48,"s":[225,35],"i":{"x":[1,1],"y":[1,1]},"o":{"x":[0,0],"y":[0,0]}},{"t":494.4,"s":[225,35],"h":1}]},"p":{"a":1,"k":[{"t":0,"s":[275,755],"i":{"x":[0.959,0.676],"y":[0.959,0.341]},"o":{"x":[0.588,0.343],"y":[0.742,0.005]}},{"t":0.978,"s":[274.999,754.888584534059],"i":{"x":[1,0.673],"y":[1,0.584]},"o":{"x":[0,0.34],"y":[0,0.25]}},{"t":1.614,"s":[274.998,754.6885399807945],"h":1},{"t":1.614,"s":[274.998,754.6885399818048],"i":{"x":[1,0.68],"y":[1,0.576]},"o":{"x":[0,0.347],"y":[0,0.241]}},{"t":2.796,"s":[274.999,754.0083476403613],"h":1},{"t":2.796,"s":[274.999,754.0083476468476],"i":{"x":[1,0.674],"y":[1,0.634]},"o":{"x":[0,0.34],"y":[0,0.301]}},{"t":3.372,"s":[274.999,753.5111411321411],"h":1},{"t":3.372,"s":[274.999,753.5111411290565],"i":{"x":[1,0.668],"y":[1,0.66]},"o":{"x":[0,0.335],"y":[0,0.326]}},{"t":3.51,"s":[275,753.3740469880162],"h":1},{"t":3.51,"s":[275,753.3740469874117],"i":{"x":[0.919,0.684],"y":[0.809,0.612]},"o":{"x":[0.137,0.351],"y":[0.02,0.278]}},{"t":4.794,"s":[275.004,751.7207468786786],"h":1},{"t":4.794,"s":[275.004,751.72074687632],"i":{"x":[1,0.669],"y":[1,0.661]},"o":{"x":[0,0.336],"y":[0,0.328]}},{"t":4.95,"s":[275.005,751.4683332427786],"h":1},{"t":4.95,"s":[275.005,751.4683332350264],"i":{"x":[1,0.669],"y":[1,0.661]},"o":{"x":[0,0.336],"y":[0,0.327]}},{"t":5.112,"s":[275.005,751.1930462506406],"h":1},{"t":5.112,"s":[275.005,751.1930462493907],"i":{"x":[1,0.672],"y":[1,0.655]},"o":{"x":[0,0.338],"y":[0,0.322]}},{"t":5.436,"s":[275.007,750.6003238173652],"h":1},{"t":5.436,"s":[275.007,750.6003238114081],"i":{"x":[0.919,0.672],"y":[0.901,0.656]},"o":{"x":[0,0.338],"y":[0,0.323]}},{"t":5.754,"s":[275.009,749.9605799479583],"h":1},{"t":5.754,"s":[275.009,749.9605799498693],"i":{"x":[1,0.672],"y":[1,0.657]},"o":{"x":[0,0.339],"y":[0,0.323]}},{"t":6.072,"s":[275.012,749.2590249027244],"h":1},{"t":6.072,"s":[275.012,749.2590249085401],"i":{"x":[0.764,0.716],"y":[0.558,0.602]},"o":{"x":[0.213,0.387],"y":[0.078,0.264]}},{"t":8.64,"s":[275.051,740.5790884402581],"h":1},{"t":8.64,"s":[275.051,740.5790884314094],"i":{"x":[0.575,0.738],"y":[0.259,0.616]},"o":{"x":[0.034,0.419],"y":[0.02,0.277]}},{"t":11.208,"s":[275.176,722.1424591956221],"h":1},{"t":11.208,"s":[275.176,722.1424591577155],"i":{"x":[0.443,0.708],"y":[0.378,0.646]},"o":{"x":[0.282,0.385],"y":[0.233,0.31]}},{"t":12.486,"s":[275.308,705.3862460274246],"h":1},{"t":12.486,"s":[275.308,705.3862460303786],"i":{"x":[0.737,0.672],"y":[0.993,0.653]},"o":{"x":[0.508,0.359],"y":[0.837,0.317]}},{"t":13.77,"s":[275.397,682.2192508858056],"h":1},{"t":13.77,"s":[275.397,682.2192509452232],"i":{"x":[0.835,0.632],"y":[0.761,0.664]},"o":{"x":[0.406,0.31],"y":[0.009,0.328]}},{"t":14.838,"s":[275.344,662.9553808101317],"h":1},{"t":14.838,"s":[275.344,662.9553808037257],"i":{"x":[1,0.646],"y":[1,0.667]},"o":{"x":[0,0.314],"y":[0,0.333]}},{"t":15.378,"s":[275.302,654.5666536255212],"h":1},{"t":15.378,"s":[275.302,654.5666536680143],"i":{"x":[1,0.646],"y":[1,0.668]},"o":{"x":[0,0.314],"y":[0,0.334]}},{"t":15.912,"s":[275.263,647.2391369218094],"h":1},{"t":15.912,"s":[275.263,647.2391368960426],"i":{"x":[0.677,0.596],"y":[0.795,0.677]},"o":{"x":[0.216,0.272],"y":[0.319,0.341]}},{"t":18.048,"s":[275.156,625.263822342725],"h":1},{"t":18.048,"s":[275.156,625.2638223848492],"i":{"x":[0.4,0.582],"y":[0.643,0.697]},"o":{"x":[0.222,0.258],"y":[0.349,0.358]}},{"t":22.326,"s":[275.069,599.899427094176],"h":1},{"t":22.326,"s":[275.069,599.8994270870921],"i":{"x":[1,0.659],"y":[1,0.671]},"o":{"x":[0,0.326],"y":[0,0.337]}},{"t":22.866,"s":[275.064,597.6553830277514],"h":1},{"t":22.866,"s":[275.064,597.6553830481064],"i":{"x":[1,0.66],"y":[1,0.671]},"o":{"x":[0,0.326],"y":[0,0.337]}},{"t":23.4,"s":[275.058,595.5792639660774],"h":1},{"t":23.4,"s":[275.058,595.5792639538773],"i":{"x":[1,0.663],"y":[1,0.669]},"o":{"x":[0,0.33],"y":[0,0.335]}},{"t":23.664,"s":[275.056,594.601456505975],"h":1},{"t":23.664,"s":[275.056,594.6014565067286],"i":{"x":[1,0.666],"y":[1,0.667]},"o":{"x":[0,0.333],"y":[0,0.334]}},{"t":23.73,"s":[275.056,594.3617887402099],"h":1},{"t":23.73,"s":[275.056,594.3617887385187],"i":{"x":[1,0.666],"y":[1,0.667]},"o":{"x":[0,0.332],"y":[0,0.334]}},{"t":23.802,"s":[275.055,594.1024677493365],"h":1},{"t":23.802,"s":[275.055,594.1024677461295],"i":{"x":[1,0.665],"y":[1,0.668]},"o":{"x":[0,0.332],"y":[0,0.334]}},{"t":23.934,"s":[275.054,593.6327474134105],"h":1},{"t":23.934,"s":[275.054,593.6327473900278],"i":{"x":[1,0.664],"y":[1,0.669]},"o":{"x":[0,0.33],"y":[0,0.335]}},{"t":24.198,"s":[275.052,592.7148952239486],"h":1},{"t":24.198,"s":[275.052,592.7148952253239],"i":{"x":[1,0.664],"y":[1,0.669]},"o":{"x":[0,0.33],"y":[0,0.335]}},{"t":24.468,"s":[275.05,591.80493090011],"h":1},{"t":24.468,"s":[275.05,591.804930925174],"i":{"x":[1,0.661],"y":[1,0.671]},"o":{"x":[0,0.327],"y":[0,0.338]}},{"t":25.002,"s":[275.046,590.0862747990687],"h":1},{"t":25.002,"s":[275.046,590.0862747924286],"i":{"x":[1,0.664],"y":[1,0.669]},"o":{"x":[0,0.33],"y":[0,0.336]}},{"t":25.272,"s":[275.044,589.256132709465],"h":1},{"t":25.272,"s":[275.044,589.2561327170861],"i":{"x":[1,0.664],"y":[1,0.669]},"o":{"x":[0,0.331],"y":[0,0.335]}},{"t":25.536,"s":[275.042,588.4683838000369],"h":1},{"t":25.536,"s":[275.042,588.4683837875355],"i":{"x":[1,0.661],"y":[1,0.671]},"o":{"x":[0,0.328],"y":[0,0.338]}},{"t":26.07,"s":[275.039,586.9438304131719],"h":1},{"t":26.07,"s":[275.039,586.9438304389585],"i":{"x":[1,0.661],"y":[1,0.671]},"o":{"x":[0,0.328],"y":[0,0.338]}},{"t":26.61,"s":[275.036,585.4903252641855],"h":1},{"t":26.61,"s":[275.036,585.4903252420688],"i":{"x":[0.737,0.631],"y":[0.843,0.708]},"o":{"x":[0.09,0.299],"y":[0.172,0.372]}},{"t":30.888,"s":[275.02,576.5076277192852],"h":1},{"t":30.888,"s":[275.02,576.5076277238412],"i":{"x":[1,0.665],"y":[1,0.669]},"o":{"x":[0,0.331],"y":[0,0.336]}},{"t":31.152,"s":[275.019,576.0749352750574],"h":1},{"t":31.152,"s":[275.019,576.0749352574815],"i":{"x":[1,0.665],"y":[1,0.67]},"o":{"x":[0,0.331],"y":[0,0.336]}},{"t":31.422,"s":[275.019,575.6447252627793],"h":1},{"t":31.422,"s":[275.019,575.6447252696541],"i":{"x":[1,0.665],"y":[1,0.67]},"o":{"x":[0,0.332],"y":[0,0.336]}},{"t":31.686,"s":[275.018,575.2358160222198],"h":1},{"t":31.686,"s":[275.018,575.2358160425454],"i":{"x":[1,0.665],"y":[1,0.67]},"o":{"x":[0,0.332],"y":[0,0.336]}},{"t":31.956,"s":[275.017,574.8293217069377],"h":1},{"t":31.956,"s":[275.017,574.8293217022934],"i":{"x":[1,0.663],"y":[1,0.673]},"o":{"x":[0,0.33],"y":[0,0.339]}},{"t":32.49,"s":[275.016,574.0591051070132],"h":1},{"t":32.49,"s":[275.016,574.0591051009623],"i":{"x":[1,0.666],"y":[1,0.668]},"o":{"x":[0,0.332],"y":[0,0.335]}},{"t":32.622,"s":[275.016,573.8754295587748],"h":1},{"t":32.622,"s":[275.016,573.8754295751826],"i":{"x":[1,0.666],"y":[1,0.668]},"o":{"x":[0,0.332],"y":[0,0.335]}},{"t":32.76,"s":[275.015,573.6861834855359],"h":1},{"t":32.76,"s":[275.015,573.6861834866577],"i":{"x":[1,0.665],"y":[1,0.67]},"o":{"x":[0,0.332],"y":[0,0.336]}},{"t":33.024,"s":[275.015,573.3319377198249],"h":1},{"t":33.024,"s":[275.015,573.3319377173082],"i":{"x":[1,0.663],"y":[1,0.673]},"o":{"x":[0,0.33],"y":[0,0.34]}},{"t":33.558,"s":[275.014,572.6458384430043],"h":1},{"t":33.558,"s":[275.014,572.6458384269677],"i":{"x":[1,0.663],"y":[1,0.673]},"o":{"x":[0,0.33],"y":[0,0.34]}},{"t":34.092,"s":[275.013,571.9989676652626],"h":1},{"t":34.092,"s":[275.013,571.998967670967],"i":{"x":[1,0.66],"y":[1,0.681]},"o":{"x":[0,0.327],"y":[0,0.347]}},{"t":35.166,"s":[275.011,570.8099367791542],"h":1},{"t":35.166,"s":[275.011,570.8099367816681],"i":{"x":[0.839,0.644],"y":[0.917,0.737]},"o":{"x":[0.044,0.312],"y":[0.108,0.401]}},{"t":39.444,"s":[275.005,567.3542636334889],"h":1},{"t":39.444,"s":[275.005,567.35426363668],"i":{"x":[0.339,0.632],"y":[0.592,0.999]},"o":{"x":[0.037,0.3],"y":[0.037,0.651]}},{"t":48,"s":[275,565],"i":{"x":[1,1],"y":[1,1]},"o":{"x":[0,0],"y":[0,0]}},{"t":60,"s":[275,565],"i":{"x":[1,0],"y":[1,1]},"o":{"x":[0,0.5],"y":[0,0]}},{"t":108,"s":[275,465],"i":{"x":[1,1],"y":[1,1]},"o":{"x":[0,0],"y":[0,0]}},{"t":494.4,"s":[275,465],"h":1}]},"r":{"a":0,"k":90}},"ip":0,"op":495.4,"st":0},{"ind":11,"ty":4,"parent":10,"ks":{},"ip":0,"op":495.4,"st":0,"shapes":[{"ty":"rc","p":{"a":1,"k":[{"t":0,"s":[225,35],"i":{"x":[0,1],"y":[1,1]},"o":{"x":[0.5,0],"y":[0,0]}},{"t":48,"s":[35,35],"i":{"x":[1,1],"y":[1,1]},"o":{"x":[0,0],"y":[0,0]}},{"t":60,"s":[35,35],"i":{"x":[1,0],"y":[1,1]},"o":{"x":[0,0.5],"y":[0,0]}},{"t":108,"s":[35,225],"i":{"x":[1,1],"y":[1,1]},"o":{"x":[0,0],"y":[0,0]}},{"t":494.4,"s":[35,225],"h":1}]},"r":{"a":0,"k":0},"s":{"a":1,"k":[{"t":0,"s":[450,70],"i":{"x":[0,1],"y":[1,1]},"o":{"x":[0.5,0],"y":[0,0]}},{"t":48,"s":[70,70],"i":{"x":[1,1],"y":[1,1]},"o":{"x":[0,0],"y":[0,0]}},{"t":60,"s":[70,70],"i":{"x":[1,0],"y":[1,1]},"o":{"x":[0,0.5],"y":[0,0]}},{"t":108,"s":[70,450],"i":{"x":[1,1],"y":[1,1]},"o":{"x":[0,0],"y":[0,0]}},{"t":494.4,"s":[70,450],"h":1}]}},{"ty":"fl","c":{"a":0,"k":[0,0,0]},"o":{"a":0,"k":100}}]},{"ind":10,"ty":3,"parent":1,"ks":{"a":{"a":1,"k":[{"t":0,"s":[225,35],"i":{"x":[0,1],"y":[1,1]},"o":{"x":[0.5,0],"y":[0,0]}},{"t":48,"s":[35,35],"i":{"x":[1,1],"y":[1,1]},"o":{"x":[0,0],"y":[0,0]}},{"t":60,"s":[35,35],"i":{"x":[1,0],"y":[1,1]},"o":{"x":[0,0.5],"y":[0,0]}},{"t":108,"s":[35,225],"i":{"x":[1,1],"y":[1,1]},"o":{"x":[0,0],"y":[0,0]}},{"t":494.4,"s":[35,225],"h":1}]},"p":{"a":1,"k":[{"t":0,"s":[275,465],"i":{"x":[1,0.676],"y":[1,0.347]},"o":{"x":[0,0.343],"y":[0,0.011]}},{"t":0.978,"s":[275.001,464.8870293382576],"i":{"x":[1,0.673],"y":[1,0.585]},"o":{"x":[0,0.34],"y":[0,0.251]}},{"t":1.614,"s":[275.002,464.68652201082637],"h":1},{"t":1.614,"s":[275.002,464.6865220120328],"i":{"x":[1,0.68],"y":[1,0.576]},"o":{"x":[0,0.347],"y":[0,0.241]}},{"t":2.796,"s":[275.001,464.0068974637742],"h":1},{"t":2.796,"s":[275.001,464.0068974661732],"i":{"x":[1,0.674],"y":[1,0.634]},"o":{"x":[0,0.34],"y":[0,0.301]}},{"t":3.372,"s":[275.001,463.5107873106928],"h":1},{"t":3.372,"s":[275.001,463.5107873052516],"i":{"x":[1,0.668],"y":[1,0.66]},"o":{"x":[0,0.335],"y":[0,0.326]}},{"t":3.51,"s":[275,463.37404949389884],"h":1},{"t":3.51,"s":[275,463.3740494868562],"i":{"x":[0.919,0.684],"y":[0.809,0.612]},"o":{"x":[0.137,0.351],"y":[0.02,0.278]}},{"t":4.794,"s":[274.996,461.72615963607785],"h":1},{"t":4.794,"s":[274.996,461.7261596431623],"i":{"x":[1,0.669],"y":[1,0.661]},"o":{"x":[0,0.336],"y":[0,0.328]}},{"t":4.95,"s":[274.995,461.47470369873827],"h":1},{"t":4.95,"s":[274.995,461.4747036888998],"i":{"x":[1,0.669],"y":[1,0.661]},"o":{"x":[0,0.336],"y":[0,0.327]}},{"t":5.112,"s":[274.995,461.2004918159842],"h":1},{"t":5.112,"s":[274.995,461.2004918125584],"i":{"x":[1,0.672],"y":[1,0.655]},"o":{"x":[0,0.338],"y":[0,0.322]}},{"t":5.436,"s":[274.993,460.6101832722948],"h":1},{"t":5.436,"s":[274.993,460.6101832731462],"i":{"x":[1,0.672],"y":[1,0.656]},"o":{"x":[0,0.338],"y":[0,0.323]}},{"t":5.754,"s":[274.991,459.97318152713484],"h":1},{"t":5.754,"s":[274.991,459.9731815330147],"i":{"x":[1,0.672],"y":[1,0.657]},"o":{"x":[0,0.339],"y":[0,0.323]}},{"t":6.072,"s":[274.988,459.27477944138883],"h":1},{"t":6.072,"s":[274.988,459.2747794437154],"i":{"x":[0.764,0.716],"y":[0.558,0.602]},"o":{"x":[0.213,0.387],"y":[0.078,0.265]}},{"t":8.64,"s":[274.949,450.6431801627692],"h":1},{"t":8.64,"s":[274.949,450.6431801663436],"i":{"x":[0.575,0.738],"y":[0.259,0.616]},"o":{"x":[0.034,0.418],"y":[0.02,0.277]}},{"t":11.208,"s":[274.824,432.3469362088168],"h":1},{"t":11.208,"s":[274.824,432.3469362118154],"i":{"x":[0.443,0.708],"y":[0.378,0.646]},"o":{"x":[0.282,0.385],"y":[0.233,0.31]}},{"t":12.486,"s":[274.692,415.7252403446368],"h":1},{"t":12.486,"s":[274.692,415.72524036674315],"i":{"x":[0.737,0.673],"y":[0.993,0.653]},"o":{"x":[0.508,0.36],"y":[0.837,0.316]}},{"t":13.77,"s":[274.603,392.630675983417],"h":1},{"t":13.77,"s":[274.603,392.63067594804215],"i":{"x":[0.835,0.632],"y":[0.761,0.663]},"o":{"x":[0.406,0.311],"y":[0.009,0.328]}},{"t":14.838,"s":[274.656,373.2937201589462],"h":1},{"t":14.838,"s":[274.656,373.2937202051261],"i":{"x":[1,0.646],"y":[1,0.667]},"o":{"x":[0,0.314],"y":[0,0.333]}},{"t":15.378,"s":[274.698,364.85630663921893],"h":1},{"t":15.378,"s":[274.698,364.85630660424476],"i":{"x":[1,0.646],"y":[1,0.668]},"o":{"x":[0,0.314],"y":[0,0.334]}},{"t":15.912,"s":[274.737,357.48592889720203],"h":1},{"t":15.912,"s":[274.737,357.48592891915854],"i":{"x":[0.677,0.596],"y":[0.795,0.677]},"o":{"x":[0.216,0.272],"y":[0.319,0.341]}},{"t":18.048,"s":[274.844,335.4022437960564],"h":1},{"t":18.048,"s":[274.844,335.4022438047313],"i":{"x":[0.4,0.581],"y":[0.643,0.697]},"o":{"x":[0.222,0.258],"y":[0.349,0.358]}},{"t":22.326,"s":[274.931,309.9604831629216],"h":1},{"t":22.326,"s":[274.931,309.960483150356],"i":{"x":[1,0.659],"y":[1,0.671]},"o":{"x":[0,0.326],"y":[0,0.337]}},{"t":22.866,"s":[274.936,307.71164946200804],"h":1},{"t":22.866,"s":[274.936,307.7116494765486],"i":{"x":[1,0.66],"y":[1,0.671]},"o":{"x":[0,0.326],"y":[0,0.337]}},{"t":23.4,"s":[274.942,305.63133994132784],"h":1},{"t":23.4,"s":[274.942,305.6313399343056],"i":{"x":[1,0.663],"y":[1,0.669]},"o":{"x":[0,0.33],"y":[0,0.335]}},{"t":23.664,"s":[274.944,304.6516354619898],"h":1},{"t":23.664,"s":[274.944,304.6516354489138],"i":{"x":[1,0.666],"y":[1,0.667]},"o":{"x":[0,0.333],"y":[0,0.334]}},{"t":23.73,"s":[274.944,304.4115099786648],"h":1},{"t":23.73,"s":[274.944,304.41150996112196],"i":{"x":[1,0.666],"y":[1,0.667]},"o":{"x":[0,0.332],"y":[0,0.334]}},{"t":23.802,"s":[274.945,304.15169691175447],"h":1},{"t":23.802,"s":[274.945,304.15169691596236],"i":{"x":[1,0.665],"y":[1,0.668]},"o":{"x":[0,0.332],"y":[0,0.334]}},{"t":23.934,"s":[274.946,303.6810936247763],"h":1},{"t":23.934,"s":[274.946,303.6810936575064],"i":{"x":[1,0.664],"y":[1,0.669]},"o":{"x":[0,0.33],"y":[0,0.335]}},{"t":24.198,"s":[274.948,302.7615466417653],"h":1},{"t":24.198,"s":[274.948,302.7615466243039],"i":{"x":[1,0.664],"y":[1,0.669]},"o":{"x":[0,0.33],"y":[0,0.335]}},{"t":24.468,"s":[274.95,301.8499409591033],"h":1},{"t":24.468,"s":[274.95,301.84994096518835],"i":{"x":[1,0.661],"y":[1,0.671]},"o":{"x":[0,0.327],"y":[0,0.338]}},{"t":25.002,"s":[274.954,300.12828671045156],"h":1},{"t":25.002,"s":[274.954,300.12828668909344],"i":{"x":[1,0.664],"y":[1,0.669]},"o":{"x":[0,0.33],"y":[0,0.336]}},{"t":25.272,"s":[274.956,299.29674237410063],"h":1},{"t":25.272,"s":[274.956,299.2967423611103],"i":{"x":[1,0.664],"y":[1,0.669]},"o":{"x":[0,0.331],"y":[0,0.335]}},{"t":25.536,"s":[274.958,298.5076893948195],"h":1},{"t":25.536,"s":[274.958,298.5076894346587],"i":{"x":[1,0.661],"y":[1,0.671]},"o":{"x":[0,0.328],"y":[0,0.338]}},{"t":26.07,"s":[274.961,296.9806828841379],"h":1},{"t":26.07,"s":[274.961,296.98068288294667],"i":{"x":[1,0.661],"y":[1,0.671]},"o":{"x":[0,0.328],"y":[0,0.338]}},{"t":26.61,"s":[274.964,295.5249210318],"h":1},{"t":26.61,"s":[274.964,295.5249210210833],"i":{"x":[0.737,0.631],"y":[0.843,0.708]},"o":{"x":[0.09,0.299],"y":[0.172,0.372]}},{"t":30.888,"s":[274.98,286.5296723854181],"h":1},{"t":30.888,"s":[274.98,286.5296723894984],"i":{"x":[1,0.665],"y":[1,0.669]},"o":{"x":[0,0.331],"y":[0,0.336]}},{"t":31.152,"s":[274.981,286.09641556941256],"h":1},{"t":31.152,"s":[274.981,286.0964155739203],"i":{"x":[1,0.665],"y":[1,0.67]},"o":{"x":[0,0.331],"y":[0,0.336]}},{"t":31.422,"s":[274.981,285.6656456981481],"h":1},{"t":31.422,"s":[274.981,285.665645683845],"i":{"x":[1,0.665],"y":[1,0.67]},"o":{"x":[0,0.332],"y":[0,0.336]}},{"t":31.686,"s":[274.982,285.2562050137111],"h":1},{"t":31.686,"s":[274.982,285.2562050328854],"i":{"x":[1,0.665],"y":[1,0.67]},"o":{"x":[0,0.332],"y":[0,0.336]}},{"t":31.956,"s":[274.983,284.84918267058856],"h":1},{"t":31.956,"s":[274.983,284.84918267634976],"i":{"x":[1,0.663],"y":[1,0.673]},"o":{"x":[0,0.33],"y":[0,0.339]}},{"t":32.49,"s":[274.984,284.0779645665831],"h":1},{"t":32.49,"s":[274.984,284.077964557475],"i":{"x":[1,0.666],"y":[1,0.668]},"o":{"x":[0,0.332],"y":[0,0.335]}},{"t":32.622,"s":[274.984,283.89404966485785],"h":1},{"t":32.622,"s":[274.984,283.8940496683713],"i":{"x":[1,0.666],"y":[1,0.668]},"o":{"x":[0,0.332],"y":[0,0.335]}},{"t":32.76,"s":[274.985,283.70455664362197],"h":1},{"t":32.76,"s":[274.985,283.7045566405509],"i":{"x":[1,0.665],"y":[1,0.67]},"o":{"x":[0,0.332],"y":[0,0.336]}},{"t":33.024,"s":[274.985,283.34984751253825],"h":1},{"t":33.024,"s":[274.985,283.34984749789794],"i":{"x":[1,0.663],"y":[1,0.673]},"o":{"x":[0,0.33],"y":[0,0.34]}},{"t":33.558,"s":[274.986,282.6628450393614],"h":1},{"t":33.558,"s":[274.986,282.66284506115153],"i":{"x":[1,0.663],"y":[1,0.673]},"o":{"x":[0,0.33],"y":[0,0.34]}},{"t":34.092,"s":[274.987,282.0151127545703],"h":1},{"t":34.092,"s":[274.987,282.01511274768626],"i":{"x":[1,0.66],"y":[1,0.681]},"o":{"x":[0,0.327],"y":[0,0.347]}},{"t":35.166,"s":[274.989,280.82445824748504],"h":1},{"t":35.166,"s":[274.989,280.82445823740466],"i":{"x":[0.839,0.644],"y":[0.917,0.737]},"o":{"x":[0.044,0.312],"y":[0.108,0.401]}},{"t":39.444,"s":[274.995,277.3633092897797],"h":1},{"t":39.444,"s":[274.995,277.36330929782156],"i":{"x":[0.339,0.632],"y":[0.592,0.998]},"o":{"x":[0.037,0.3],"y":[0.037,0.65]}},{"t":48,"s":[275,275],"i":{"x":[1,1],"y":[1,1]},"o":{"x":[0,0],"y":[0,0]}},{"t":60,"s":[275,275],"i":{"x":[0.676,0.959],"y":[0.347,0.959]},"o":{"x":[0.343,0.588],"y":[0.011,0.742]}},{"t":60.978,"s":[275.11288318962596,274.999],"i":{"x":[0.673,1],"y":[0.585,1]},"o":{"x":[0.34,0],"y":[0.251,0]}},{"t":61.614,"s":[275.3132318587009,274.998],"h":1},{"t":61.614,"s":[275.31323185733567,274.998],"i":{"x":[0.68,1],"y":[0.576,1]},"o":{"x":[0.347,0],"y":[0.241,0]}},{"t":62.796,"s":[275.9923085481457,274.999],"h":1},{"t":62.796,"s":[275.9923085529675,274.999],"i":{"x":[0.674,1],"y":[0.634,1]},"o":{"x":[0.34,0],"y":[0.301,0]}},{"t":63.372,"s":[276.4880124793105,274.999],"h":1},{"t":63.372,"s":[276.48801248610255,274.999],"i":{"x":[0.668,1],"y":[0.66,1]},"o":{"x":[0.335,0],"y":[0.326,0]}},{"t":63.51,"s":[276.62463759621653,275],"h":1},{"t":63.51,"s":[276.62463758909826,275],"i":{"x":[0.684,0.919],"y":[0.612,0.809]},"o":{"x":[0.351,0.137],"y":[0.278,0.02]}},{"t":64.794,"s":[278.2711489972673,275.004],"h":1},{"t":64.794,"s":[278.2711489922346,275.004],"i":{"x":[0.669,1],"y":[0.661,1]},"o":{"x":[0.336,0],"y":[0.328,0]}},{"t":64.95,"s":[278.52239179477704,275.005],"h":1},{"t":64.95,"s":[278.5223917816839,275.005],"i":{"x":[0.669,1],"y":[0.661,1]},"o":{"x":[0.336,0],"y":[0.327,0]}},{"t":65.112,"s":[278.7963704700047,275.005],"h":1},{"t":65.112,"s":[278.7963704643584,275.005],"i":{"x":[0.672,1],"y":[0.655,1]},"o":{"x":[0.338,0],"y":[0.322,0]}},{"t":65.436,"s":[279.38617456648063,275.007],"h":1},{"t":65.436,"s":[279.38617457809613,275.007],"i":{"x":[0.672,0.919],"y":[0.656,0.901]},"o":{"x":[0.338,0],"y":[0.323,0]}},{"t":65.754,"s":[280.0226284983119,275.009],"h":1},{"t":65.754,"s":[280.0226284806285,275.009],"i":{"x":[0.672,1],"y":[0.657,1]},"o":{"x":[0.339,0],"y":[0.323,0]}},{"t":66.072,"s":[280.72042614694675,275.012],"h":1},{"t":66.072,"s":[280.7204261591036,275.012],"i":{"x":[0.716,0.764],"y":[0.602,0.558]},"o":{"x":[0.387,0.213],"y":[0.265,0.078]}},{"t":68.64,"s":[289.3443609628283,275.051],"h":1},{"t":68.64,"s":[289.34436098768055,275.051],"i":{"x":[0.738,0.575],"y":[0.616,0.259]},"o":{"x":[0.418,0.034],"y":[0.277,0.02]}},{"t":71.208,"s":[307.6254696914144,275.176],"h":1},{"t":71.208,"s":[307.6254696576131,275.176],"i":{"x":[0.708,0.443],"y":[0.646,0.378]},"o":{"x":[0.386,0.282],"y":[0.31,0.233]}},{"t":72.486,"s":[324.240544875341,275.308],"h":1},{"t":72.486,"s":[324.2405449010039,275.308],"i":{"x":[0.673,0.737],"y":[0.653,0.993]},"o":{"x":[0.36,0.508],"y":[0.316,0.837]}},{"t":73.77,"s":[347.34627992041925,275.397],"h":1},{"t":73.77,"s":[347.34627991888897,275.397],"i":{"x":[0.632,0.835],"y":[0.663,0.761]},"o":{"x":[0.311,0.406],"y":[0.328,0.009]}},{"t":74.838,"s":[366.70150981359853,275.344],"h":1},{"t":74.838,"s":[366.70150981138033,275.344],"i":{"x":[0.646,1],"y":[0.667,1]},"o":{"x":[0.314,0],"y":[0.333,0]}},{"t":75.378,"s":[375.1454936006706,275.302],"h":1},{"t":75.378,"s":[375.1454936271136,275.302],"i":{"x":[0.646,1],"y":[0.668,1]},"o":{"x":[0.314,0],"y":[0.334,0]}},{"t":75.912,"s":[382.5202783250156,275.263],"h":1},{"t":75.912,"s":[382.5202783078161,275.263],"i":{"x":[0.596,0.677],"y":[0.677,0.795]},"o":{"x":[0.272,0.216],"y":[0.341,0.319]}},{"t":78.048,"s":[404.61008031014865,275.156],"h":1},{"t":78.048,"s":[404.6100803305917,275.156],"i":{"x":[0.581,0.4],"y":[0.697,0.643]},"o":{"x":[0.258,0.222],"y":[0.358,0.349]}},{"t":82.326,"s":[430.04981939659064,275.069],"h":1},{"t":82.326,"s":[430.04981937741775,275.069],"i":{"x":[0.659,1],"y":[0.671,1]},"o":{"x":[0.326,0],"y":[0.337,0]}},{"t":82.866,"s":[432.29818545989383,275.064],"h":1},{"t":82.866,"s":[432.2981854911534,275.064],"i":{"x":[0.66,1],"y":[0.671,1]},"o":{"x":[0.326,0],"y":[0.337,0]}},{"t":83.4,"s":[434.37803188175997,275.058],"h":1},{"t":83.4,"s":[434.37803187771397,275.058],"i":{"x":[0.663,1],"y":[0.669,1]},"o":{"x":[0.33,0],"y":[0.335,0]}},{"t":83.664,"s":[435.35750855602424,275.056],"h":1},{"t":83.664,"s":[435.35750855984463,275.056],"i":{"x":[0.666,1],"y":[0.667,1]},"o":{"x":[0.333,0],"y":[0.334,0]}},{"t":83.73,"s":[435.59757728786053,275.056],"h":1},{"t":83.73,"s":[435.597577260759,275.056],"i":{"x":[0.666,1],"y":[0.667,1]},"o":{"x":[0.332,0],"y":[0.334,0]}},{"t":83.802,"s":[435.8573285190919,275.055],"h":1},{"t":83.802,"s":[435.85732855161496,275.055],"i":{"x":[0.665,1],"y":[0.668,1]},"o":{"x":[0.332,0],"y":[0.334,0]}},{"t":83.934,"s":[436.32781886141845,275.054],"h":1},{"t":83.934,"s":[436.32781886107875,275.054],"i":{"x":[0.664,1],"y":[0.669,1]},"o":{"x":[0.33,0],"y":[0.335,0]}},{"t":84.198,"s":[437.24714126792674,275.052],"h":1},{"t":84.198,"s":[437.24714123805467,275.052],"i":{"x":[0.664,1],"y":[0.669,1]},"o":{"x":[0.33,0],"y":[0.335,0]}},{"t":84.468,"s":[438.1585193377764,275.05],"h":1},{"t":84.468,"s":[438.15851934764873,275.05],"i":{"x":[0.661,1],"y":[0.671,1]},"o":{"x":[0.327,0],"y":[0.338,0]}},{"t":85.002,"s":[439.8797309358064,275.046],"h":1},{"t":85.002,"s":[439.87973095443834,275.046],"i":{"x":[0.664,1],"y":[0.669,1]},"o":{"x":[0.33,0],"y":[0.336,0]}},{"t":85.272,"s":[440.7110556230662,275.044],"h":1},{"t":85.272,"s":[440.7110556329,275.044],"i":{"x":[0.664,1],"y":[0.669,1]},"o":{"x":[0.331,0],"y":[0.335,0]}},{"t":85.536,"s":[441.4998967670631,275.042],"h":1},{"t":85.536,"s":[441.4998967312305,275.042],"i":{"x":[0.661,1],"y":[0.671,1]},"o":{"x":[0.328,0],"y":[0.338,0]}},{"t":86.07,"s":[443.026484149671,275.039],"h":1},{"t":86.07,"s":[443.0264841629774,275.039],"i":{"x":[0.661,1],"y":[0.671,1]},"o":{"x":[0.328,0],"y":[0.338,0]}},{"t":86.61,"s":[444.48183554395575,275.036],"h":1},{"t":86.61,"s":[444.4818355319553,275.036],"i":{"x":[0.631,0.737],"y":[0.708,0.843]},"o":{"x":[0.299,0.09],"y":[0.372,0.172]}},{"t":90.888,"s":[453.4743338660562,275.02],"h":1},{"t":90.888,"s":[453.474333856738,275.02],"i":{"x":[0.665,1],"y":[0.669,1]},"o":{"x":[0.331,0],"y":[0.336,0]}},{"t":91.152,"s":[453.90744963085723,275.019],"h":1},{"t":91.152,"s":[453.90744962317285,275.019],"i":{"x":[0.665,1],"y":[0.67,1]},"o":{"x":[0.331,0],"y":[0.336,0]}},{"t":91.422,"s":[454.33807852394165,275.019],"h":1},{"t":91.422,"s":[454.3380785547425,275.019],"i":{"x":[0.665,1],"y":[0.67,1]},"o":{"x":[0.332,0],"y":[0.336,0]}},{"t":91.686,"s":[454.7473845576457,275.018],"h":1},{"t":91.686,"s":[454.74738455764907,275.018],"i":{"x":[0.665,1],"y":[0.67,1]},"o":{"x":[0.332,0],"y":[0.336,0]}},{"t":91.956,"s":[455.1542723942481,275.017],"h":1},{"t":91.956,"s":[455.1542723726159,275.017],"i":{"x":[0.663,1],"y":[0.673,1]},"o":{"x":[0.33,0],"y":[0.339,0]}},{"t":92.49,"s":[455.9252338323766,275.016],"h":1},{"t":92.49,"s":[455.9252338274471,275.016],"i":{"x":[0.666,1],"y":[0.668,1]},"o":{"x":[0.332,0],"y":[0.335,0]}},{"t":92.622,"s":[456.109087177874,275.016],"h":1},{"t":92.622,"s":[456.109087198637,275.016],"i":{"x":[0.666,1],"y":[0.668,1]},"o":{"x":[0.332,0],"y":[0.335,0]}},{"t":92.76,"s":[456.2985166780094,275.015],"h":1},{"t":92.76,"s":[456.2985166755829,275.015],"i":{"x":[0.665,1],"y":[0.67,1]},"o":{"x":[0.332,0],"y":[0.336,0]}},{"t":93.024,"s":[456.65310648158305,275.015],"h":1},{"t":93.024,"s":[456.6531064882138,275.015],"i":{"x":[0.663,1],"y":[0.673,1]},"o":{"x":[0.33,0],"y":[0.34,0]}},{"t":93.558,"s":[457.3398764735682,275.014],"h":1},{"t":93.558,"s":[457.33987647318406,275.014],"i":{"x":[0.663,1],"y":[0.673,1]},"o":{"x":[0.33,0],"y":[0.34,0]}},{"t":94.092,"s":[457.98738794075797,275.013],"h":1},{"t":94.092,"s":[457.98738794417363,275.013],"i":{"x":[0.66,1],"y":[0.681,1]},"o":{"x":[0.327,0],"y":[0.347,0]}},{"t":95.166,"s":[459.17763232169466,275.011],"h":1},{"t":95.166,"s":[459.17763230607153,275.011],"i":{"x":[0.644,0.839],"y":[0.737,0.917]},"o":{"x":[0.312,0.044],"y":[0.401,0.108]}},{"t":99.444,"s":[462.6375575304704,275.005],"h":1},{"t":99.444,"s":[462.63755753172325,275.005],"i":{"x":[0.632,0.339],"y":[0.998,0.592]},"o":{"x":[0.3,0.037],"y":[0.65,0.037]}},{"t":108,"s":[465,275],"i":{"x":[1,1],"y":[1,1]},"o":{"x":[0,0],"y":[0,0]}},{"t":494.4,"s":[465,275],"h":1}]},"r":{"a":0,"k":90}},"ip":0,"op":495.4,"st":0},{"ind":13,"ty":4,"parent":12,"ks":{},"ip":0,"op":495.4,"st":0,"shapes":[{"ty":"rc","p":{"a":1,"k":[{"t":0,"s":[225,35],"i":{"x":[1,1],"y":[1,1]},"o":{"x":[0,0],"y":[0,0]}},{"t":60,"s":[225,35],"i":{"x":[0,1],"y":[1,1]},"o":{"x":[0.5,0],"y":[0,0]}},{"t":108,"s":[35,35],"i":{"x":[1,1],"y":[1,1]},"o":{"x":[0,0],"y":[0,0]}},{"t":494.4,"s":[35,35],"h":1}]},"r":{"a":0,"k":0},"s":{"a":1,"k":[{"t":0,"s":[450,70],"i":{"x":[1,1],"y":[1,1]},"o":{"x":[0,0],"y":[0,0]}},{"t":60,"s":[450,70],"i":{"x":[0,1],"y":[1,1]},"o":{"x":[0.5,0],"y":[0,0]}},{"t":108,"s":[70,70],"i":{"x":[1,1],"y":[1,1]},"o":{"x":[0,0],"y":[0,0]}},{"t":494.4,"s":[70,70],"h":1}]}},{"ty":"fl","c":{"a":0,"k":[0,0,0]},"o":{"a":0,"k":100}}]},{"ind":12,"ty":3,"parent":1,"ks":{"p":{"a":1,"k":[{"t":0,"s":[240,240],"i":{"x":[0,1],"y":[1,1]},"o":{"x":[0.5,0],"y":[0,0]}},{"t":48,"s":[340,240],"i":{"x":[1,1],"y":[1,1]},"o":{"x":[0,0],"y":[0,0]}},{"t":60,"s":[340,240],"i":{"x":[0,1],"y":[1,1]},"o":{"x":[0.501,0],"y":[0,0]}},{"t":108,"s":[720,240],"i":{"x":[1,1],"y":[1,1]},"o":{"x":[0,0],"y":[0,0]}},{"t":494.4,"s":[720,240],"h":1}]}},"ip":0,"op":495.4,"st":0},{"ind":1,"ty":3,"parent":0,"ks":{},"ip":0,"op":495.4,"st":0},{"ind":14,"ty":4,"parent":0,"ks":{},"ip":0,"op":495.4,"st":0,"shapes":[{"ty":"rc","p":{"a":0,"k":[515,515]},"r":{"a":0,"k":0},"s":{"a":0,"k":[1030,1030]}},{"ty":"fl","c":{"a":0,"k":[0.776,0.776,0.776,0]},"o":{"a":0,"k":0}}]},{"ind":0,"ty":3,"ks":{},"ip":0,"op":495.4,"st":0}],"meta":{"g":"https://jitter.video"},"op":494.4,"v":"5.7.4","w":1030}